spaceone/__init__.py
spaceone/plugin/__init__.py
spaceone/plugin/api/__init__.py
spaceone/plugin/api/v1/__init__.py
spaceone/plugin/api/v1/plugin.py
spaceone/plugin/api/v1/supervisor.py
spaceone/plugin/conf/__init__.py
spaceone/plugin/conf/global_conf.py
spaceone/plugin/conf/proto_conf.py
spaceone/plugin/connector/__init__.py
spaceone/plugin/connector/plugin_connector.py
spaceone/plugin/error/__init__.py
spaceone/plugin/error/custom.py
spaceone/plugin/error/plugin.py
spaceone/plugin/error/supervisor.py
spaceone/plugin/info/__init__.py
spaceone/plugin/info/common_info.py
spaceone/plugin/info/plugin_info.py
spaceone/plugin/info/supervisor_info.py
spaceone/plugin/lib/__init__.py
spaceone/plugin/lib/timeout.py
spaceone/plugin/manager/__init__.py
spaceone/plugin/manager/identity_manager.py
spaceone/plugin/manager/repository_manager.py
spaceone/plugin/manager/plugin_manager/__init__.py
spaceone/plugin/manager/plugin_manager/plugin_ref_manager.py
spaceone/plugin/manager/plugin_manager/plugin_state.py
spaceone/plugin/manager/supervisor_manager/__init__.py
spaceone/plugin/manager/supervisor_manager/supervisor_state.py
spaceone/plugin/model/__init__.py
spaceone/plugin/model/installed_plugin_model.py
spaceone/plugin/model/installed_plugin_ref_model.py
spaceone/plugin/model/supervisor_model.py
spaceone/plugin/model/supervisor_ref_model.py
spaceone/plugin/scheduler/__init__.py
spaceone/plugin/scheduler/cleanup_scheduler.py
spaceone/plugin/service/__init__.py
spaceone/plugin/service/plugin_service.py
spaceone/plugin/service/supervisor_service.py
spaceone_plugin-1.12.0.dist-info/METADATA
spaceone_plugin-1.12.0.dist-info/WHEEL
spaceone_plugin-1.12.0.dist-info/top_level.txt
spaceone_plugin-1.12.0.dist-info/RECORD
